schemaspec/__init__.py
schemaspec/core.py
schemaspec/service.py
schemaspec-0.1.1.dist-info/METADATA
schemaspec-0.1.1.dist-info/WHEEL
schemaspec-0.1.1.dist-info/RECORD
